telecms_bridge/__init__.py
telecms_bridge/__main__.py
telecms_bridge/app.py
telecms_bridge/configuration.py
telecms_bridge/media.py
telecms_bridge/router.py
telecms_bridge/settings.py
telecms_bridge/__pycache__/__init__.cpython-38.pyc
telecms_bridge/commands/__init__.py
telecms_bridge/handlers/__init__.py
telecms_bridge/handlers/not_found.py
telecms_bridge/handlers/temporary_redirect.py
telecms_bridge/handlers/view.py
telecms_bridge/utils/__init__.py
telecms_bridge/utils/create_config.py
telecms_bridge/utils/settings.py
telecms_bridge-1.0.1.dist-info/LICENSE
telecms_bridge-1.0.1.dist-info/METADATA
telecms_bridge-1.0.1.dist-info/WHEEL
telecms_bridge-1.0.1.dist-info/entry_points.txt
telecms_bridge-1.0.1.dist-info/top_level.txt
telecms_bridge-1.0.1.dist-info/RECORD
