Metadata-Version: 2.1
Name: telecms-bridge
Version: 1.0.1
Home-page: https://github.com/serviceexchange/telecms-bridge
Author: Billy Truong
Author-email: support@service.exchange
License: MIT
License-File: LICENSE
Requires-Dist: tornado (==6.1)
Requires-Dist: six
Requires-Dist: telecms-bridge-base (==1.0.0)
